{"trial_id": "0034", "hyperparameters": {"space": [{"class_name": "Int", "config": {"name": "num_layers", "default": null, "conditions": [], "min_value": 1, "max_value": 3, "step": 1, "sampling": "linear"}}, {"class_name": "Int", "config": {"name": "units_0", "default": null, "conditions": [], "min_value": 32, "max_value": 256, "step": 32, "sampling": "linear"}}, {"class_name": "Boolean", "config": {"name": "batch_norm", "default": false, "conditions": []}}, {"class_name": "Float", "config": {"name": "dropout", "default": 0.1, "conditions": [], "min_value": 0.1, "max_value": 0.5, "step": 0.1, "sampling": "linear"}}, {"class_name": "Choice", "config": {"name": "learning_rate", "default": 0.01, "conditions": [], "values": [0.01, 0.001, 0.0001], "ordered": true}}, {"class_name": "Int", "config": {"name": "units_1", "default": null, "conditions": [], "min_value": 32, "max_value": 256, "step": 32, "sampling": "linear"}}, {"class_name": "Int", "config": {"name": "units_2", "default": null, "conditions": [], "min_value": 32, "max_value": 256, "step": 32, "sampling": "linear"}}], "values": {"num_layers": 3, "units_0": 96, "batch_norm": true, "dropout": 0.2, "learning_rate": 0.01, "units_1": 160, "tuner/epochs": 6, "tuner/initial_epoch": 2, "tuner/bracket": 3, "tuner/round": 1, "units_2": 32, "tuner/trial_id": "0007"}}, "metrics": {"metrics": {"accuracy": {"direction": "max", "observations": [{"value": [0.8542553186416626], "step": 2}]}, "auc": {"direction": "max", "observations": [{"value": [0.9112635254859924], "step": 2}]}, "loss": {"direction": "min", "observations": [{"value": [0.37898263335227966], "step": 2}]}, "val_accuracy": {"direction": "max", "observations": [{"value": [0.8432203531265259], "step": 2}]}, "val_auc": {"direction": "max", "observations": [{"value": [0.768208384513855], "step": 2}]}, "val_loss": {"direction": "min", "observations": [{"value": [0.4262229800224304], "step": 2}]}}}, "score": 0.768208384513855, "best_step": 2, "status": "COMPLETED", "message": null}